Workbook

Sheet Assumptions
A1: 170 Michaela Dr, Alpharetta GA 30009 — Underwriting Assumptions
A2: Edit ONLY this sheet (blue cells). All other sheets recalculate. Sources: MARKET_DATA.md, research as of July 2026.
A4: PROPERTY
A5: Ask price (relisted Feb 2026; was $2,695,000 Aug 2025) | B5: 2150000 | C5: Confirmed, FMLS 7719521
A6: Purchase price (offer basis) | B6: 1750000 | C6: Recommended MAO — see Scenarios
A7: Square feet | B7: 5120 | C7: 6bd/5.5ba, 2025 build, 0.6 ac
A8: FINANCING (bridge acquisition loan)
A9: Loan-to-cost (LTC) | B9: 0.65 | C9: Stabilized new-construction bridge
A10: Interest rate (interest-only) | B10: 0.095 | C10: Atlanta private bridge, mid-2026
A11: Origination points | B11: 0.02
A12: ACQUISITION & SETUP
A13: Closing costs (% of price) | B13: 0.0125 | C13: Title, legal, transfer, inspection
A14: Furnishing / staging budget | B14: 50000 | C14: Enables exec lease + staged sale
A15: Working capital reserve | B15: 25000
A16: CARRY (annual unless noted)
A17: Property taxes / yr (carry period) | B17: 20000 | C17: Assessed basis lags; ~$27k/yr fully reassessed non-homestead at $2.15M (31.7 mills x 40%)
A18: Insurance / yr (high-value landlord) | B18: 12000 | C18: Chubb/PURE-tier estimate
A19: Utilities + lawn + alarm / mo | B19: 750
A20: OPERATIONS (furnished executive lease)
A21: Furnished executive rent / mo | B21: 8500 | C21: vs $5.5-7.5k unfurnished market
A22: Lease-up / vacant months | B22: 3
A23: Property management (% of rent) | B23: 0.08
A24: Market rent unfurnished / mo (rental test) | B24: 6500 | C24: Comps ~$1.00-1.45/sqft
A25: EXIT
A26: Exit price (base case) | B26: 2200000 | C26: Comp support $420-470/sqft = $2.15-2.41M
A27: Hold months (base case) | B27: 12
A28: Selling costs (% of exit) | B28: 0.055 | C28: 5.0% commissions + 0.5% closing
A29: EQUITY STRUCTURE — LP SYNDICATION
A30: LP share of equity | B30: 0.9 | C30: GP co-invests 10%, first-loss
A31: LP preferred return (annualized) | B31: 0.08
A32: LP share of post-pref profit | B32: 0.7 | C32: 70/30 promote
A33: EQUITY STRUCTURE — JV ALTERNATIVE
A34: JV capital-partner preferred | B34: 0.1 | C34: Partner funds 100% of equity
A35: JV capital share post-pref | B35: 0.6 | C35: 60/40, no fees
A36: RENTAL / REFI TEST RATES
A37: DSCR loan rate | B37: 0.0725 | C37: Mid-2026, 75-80% LTV programs
A38: Investor cash-out refi rate | B38: 0.0775 | C38: 75% LTV cap

Sheet Deal Model
A1: Deal Model — Base Case (formula-driven)
A2: Strategy B: acquire at discount, furnished executive lease during hold, resale. Driven entirely by Assumptions.
A4: SOURCES & USES
A5: Purchase price | B5: =Assumptions!$B$6
A6: Closing costs | B6: =Assumptions!$B$6*Assumptions!$B$13
A7: Bridge loan | B7: =Assumptions!$B$6*Assumptions!$B$9
A8: Origination points | B8: =B7*Assumptions!$B$11
A9: Furnishing / staging | B9: =Assumptions!$B$14
A10: Working capital | B10: =Assumptions!$B$15
A11: Total equity required (cash in) | B11: =B5+B6+B8+B9+B10-B7
A12: HOLD PERIOD
A13: Interest (IO) | B13: =B7*Assumptions!$B$10*Assumptions!$B$27/12
A14: Taxes + insurance (prorated) | B14: =(Assumptions!$B$17+Assumptions!$B$18)*Assumptions!$B$27/12
A15: Utilities / lawn / alarm | B15: =Assumptions!$B$19*Assumptions!$B$27
A16: Executive lease income (net of mgmt) | B16: =MAX(0,Assumptions!$B$27-Assumptions!$B$22)*Assumptions!$B$21*(1-Assumptions!$B$23)
A17: Net carry | B17: =B13+B14+B15-B16
A18: EXIT
A19: Gross exit price | B19: =Assumptions!$B$26
A20: Selling costs | B20: =B19*Assumptions!$B$28
A21: Loan payoff | B21: =B7
A22: Net sale proceeds to equity | B22: =B19-B20-B21
A23: RETURNS (deal level)
A24: Total profit | B24: =B22-B11-B17
A25: Return on equity (hold period) | B25: =B24/B11
A26: Annualized ROE | B26: =B25*12/Assumptions!$B$27
A27: Equity multiple | B27: =1+B25
A28: Exit $/sqft | B28: =B19/Assumptions!$B$7
A29: Basis $/sqft (all-in cost / sqft) | B29: =(B5+B6+B9+B13+B17)/Assumptions!$B$7

Sheet Scenarios
A1: Scenario Grid — 2 strategies x 3 purchase prices x 3 exits
A2: Strategy A: staged vacant resale sprint (no lease, faster exit). Strategy B: furnished executive carry into spring market. Buy/Exit/Hold columns are inputs; the rest are formulas.
A4: Strategy | B4: Buy | C4: Exit scenario | D4: Exit price | E4: Hold (mo) | F4: Lease? | G4: Setup $ | H4: Loan | I4: Equity | J4: Interest | K4: Carry (tax/ins/util) | L4: Lease income (net) | M4: Sale net | N4: Profit | O4: ROE | P4: Annualized ROE | Q4: Exit $/sqft
A5: A | B5: 1750000 | C5: Bear | D5: 2050000 | E5: 10 | F5: 0 | G5: 25000 | H5: =B5*Assumptions!$B$9 | I5: =B5+B5*Assumptions!$B$13+H5*Assumptions!$B$11+G5+Assumptions!$B$15-H5 | J5: =H5*Assumptions!$B$10*E5/12 | K5: =(Assumptions!$B$17+Assumptions!$B$18)*E5/12+Assumptions!$B$19*E5 | L5: =F5*MAX(0,E5-Assumptions!$B$22)*Assumptions!$B$21*(1-Assumptions!$B$23) | M5: =D5*(1-Assumptions!$B$28) | N5: =M5-H5+L5-J5-K5-I5 | O5: =N5/I5 | P5: =O5*12/E5 | Q5: =D5/Assumptions!$B$7
A6: A | B6: 1750000 | C6: Base | D6: 2200000 | E6: 8 | F6: 0 | G6: 25000 | H6: =B6*Assumptions!$B$9 | I6: =B6+B6*Assumptions!$B$13+H6*Assumptions!$B$11+G6+Assumptions!$B$15-H6 | J6: =H6*Assumptions!$B$10*E6/12 | K6: =(Assumptions!$B$17+Assumptions!$B$18)*E6/12+Assumptions!$B$19*E6 | L6: =F6*MAX(0,E6-Assumptions!$B$22)*Assumptions!$B$21*(1-Assumptions!$B$23) | M6: =D6*(1-Assumptions!$B$28) | N6: =M6-H6+L6-J6-K6-I6 | O6: =N6/I6 | P6: =O6*12/E6 | Q6: =D6/Assumptions!$B$7
A7: A | B7: 1750000 | C7: Bull | D7: 2350000 | E7: 6 | F7: 0 | G7: 25000 | H7: =B7*Assumptions!$B$9 | I7: =B7+B7*Assumptions!$B$13+H7*Assumptions!$B$11+G7+Assumptions!$B$15-H7 | J7: =H7*Assumptions!$B$10*E7/12 | K7: =(Assumptions!$B$17+Assumptions!$B$18)*E7/12+Assumptions!$B$19*E7 | L7: =F7*MAX(0,E7-Assumptions!$B$22)*Assumptions!$B$21*(1-Assumptions!$B$23) | M7: =D7*(1-Assumptions!$B$28) | N7: =M7-H7+L7-J7-K7-I7 | O7: =N7/I7 | P7: =O7*12/E7 | Q7: =D7/Assumptions!$B$7
A8: A | B8: 1825000 | C8: Bear | D8: 2050000 | E8: 10 | F8: 0 | G8: 25000 | H8: =B8*Assumptions!$B$9 | I8: =B8+B8*Assumptions!$B$13+H8*Assumptions!$B$11+G8+Assumptions!$B$15-H8 | J8: =H8*Assumptions!$B$10*E8/12 | K8: =(Assumptions!$B$17+Assumptions!$B$18)*E8/12+Assumptions!$B$19*E8 | L8: =F8*MAX(0,E8-Assumptions!$B$22)*Assumptions!$B$21*(1-Assumptions!$B$23) | M8: =D8*(1-Assumptions!$B$28) | N8: =M8-H8+L8-J8-K8-I8 | O8: =N8/I8 | P8: =O8*12/E8 | Q8: =D8/Assumptions!$B$7
A9: A | B9: 1825000 | C9: Base | D9: 2200000 | E9: 8 | F9: 0 | G9: 25000 | H9: =B9*Assumptions!$B$9 | I9: =B9+B9*Assumptions!$B$13+H9*Assumptions!$B$11+G9+Assumptions!$B$15-H9 | J9: =H9*Assumptions!$B$10*E9/12 | K9: =(Assumptions!$B$17+Assumptions!$B$18)*E9/12+Assumptions!$B$19*E9 | L9: =F9*MAX(0,E9-Assumptions!$B$22)*Assumptions!$B$21*(1-Assumptions!$B$23) | M9: =D9*(1-Assumptions!$B$28) | N9: =M9-H9+L9-J9-K9-I9 | O9: =N9/I9 | P9: =O9*12/E9 | Q9: =D9/Assumptions!$B$7
A10: A | B10: 1825000 | C10: Bull | D10: 2350000 | E10: 6 | F10: 0 | G10: 25000 | H10: =B10*Assumptions!$B$9 | I10: =B10+B10*Assumptions!$B$13+H10*Assumptions!$B$11+G10+Assumptions!$B$15-H10 | J10: =H10*Assumptions!$B$10*E10/12 | K10: =(Assumptions!$B$17+Assumptions!$B$18)*E10/12+Assumptions!$B$19*E10 | L10: =F10*MAX(0,E10-Assumptions!$B$22)*Assumptions!$B$21*(1-Assumptions!$B$23) | M10: =D10*(1-Assumptions!$B$28) | N10: =M10-H10+L10-J10-K10-I10 | O10: =N10/I10 | P10: =O10*12/E10 | Q10: =D10/Assumptions!$B$7
A11: A | B11: 1950000 | C11: Bear | D11: 2050000 | E11: 10 | F11: 0 | G11: 25000 | H11: =B11*Assumptions!$B$9 | I11: =B11+B11*Assumptions!$B$13+H11*Assumptions!$B$11+G11+Assumptions!$B$15-H11 | J11: =H11*Assumptions!$B$10*E11/12 | K11: =(Assumptions!$B$17+Assumptions!$B$18)*E11/12+Assumptions!$B$19*E11 | L11: =F11*MAX(0,E11-Assumptions!$B$22)*Assumptions!$B$21*(1-Assumptions!$B$23) | M11: =D11*(1-Assumptions!$B$28) | N11: =M11-H11+L11-J11-K11-I11 | O11: =N11/I11 | P11: =O11*12/E11 | Q11: =D11/Assumptions!$B$7
A12: A | B12: 1950000 | C12: Base | D12: 2200000 | E12: 8 | F12: 0 | G12: 25000 | H12: =B12*Assumptions!$B$9 | I12: =B12+B12*Assumptions!$B$13+H12*Assumptions!$B$11+G12+Assumptions!$B$15-H12 | J12: =H12*Assumptions!$B$10*E12/12 | K12: =(Assumptions!$B$17+Assumptions!$B$18)*E12/12+Assumptions!$B$19*E12 | L12: =F12*MAX(0,E12-Assumptions!$B$22)*Assumptions!$B$21*(1-Assumptions!$B$23) | M12: =D12*(1-Assumptions!$B$28) | N12: =M12-H12+L12-J12-K12-I12 | O12: =N12/I12 | P12: =O12*12/E12 | Q12: =D12/Assumptions!$B$7
A13: A | B13: 1950000 | C13: Bull | D13: 2350000 | E13: 6 | F13: 0 | G13: 25000 | H13: =B13*Assumptions!$B$9 | I13: =B13+B13*Assumptions!$B$13+H13*Assumptions!$B$11+G13+Assumptions!$B$15-H13 | J13: =H13*Assumptions!$B$10*E13/12 | K13: =(Assumptions!$B$17+Assumptions!$B$18)*E13/12+Assumptions!$B$19*E13 | L13: =F13*MAX(0,E13-Assumptions!$B$22)*Assumptions!$B$21*(1-Assumptions!$B$23) | M13: =D13*(1-Assumptions!$B$28) | N13: =M13-H13+L13-J13-K13-I13 | O13: =N13/I13 | P13: =O13*12/E13 | Q13: =D13/Assumptions!$B$7
A14: B | B14: 1750000 | C14: Bear | D14: 2050000 | E14: 14 | F14: 1 | G14: 50000 | H14: =B14*Assumptions!$B$9 | I14: =B14+B14*Assumptions!$B$13+H14*Assumptions!$B$11+G14+Assumptions!$B$15-H14 | J14: =H14*Assumptions!$B$10*E14/12 | K14: =(Assumptions!$B$17+Assumptions!$B$18)*E14/12+Assumptions!$B$19*E14 | L14: =F14*MAX(0,E14-Assumptions!$B$22)*Assumptions!$B$21*(1-Assumptions!$B$23) | M14: =D14*(1-Assumptions!$B$28) | N14: =M14-H14+L14-J14-K14-I14 | O14: =N14/I14 | P14: =O14*12/E14 | Q14: =D14/Assumptions!$B$7
A15: B | B15: 1750000 | C15: Base | D15: 2200000 | E15: 12 | F15: 1 | G15: 50000 | H15: =B15*Assumptions!$B$9 | I15: =B15+B15*Assumptions!$B$13+H15*Assumptions!$B$11+G15+Assumptions!$B$15-H15 | J15: =H15*Assumptions!$B$10*E15/12 | K15: =(Assumptions!$B$17+Assumptions!$B$18)*E15/12+Assumptions!$B$19*E15 | L15: =F15*MAX(0,E15-Assumptions!$B$22)*Assumptions!$B$21*(1-Assumptions!$B$23) | M15: =D15*(1-Assumptions!$B$28) | N15: =M15-H15+L15-J15-K15-I15 | O15: =N15/I15 | P15: =O15*12/E15 | Q15: =D15/Assumptions!$B$7
A16: B | B16: 1750000 | C16: Bull | D16: 2350000 | E16: 10 | F16: 1 | G16: 50000 | H16: =B16*Assumptions!$B$9 | I16: =B16+B16*Assumptions!$B$13+H16*Assumptions!$B$11+G16+Assumptions!$B$15-H16 | J16: =H16*Assumptions!$B$10*E16/12 | K16: =(Assumptions!$B$17+Assumptions!$B$18)*E16/12+Assumptions!$B$19*E16 | L16: =F16*MAX(0,E16-Assumptions!$B$22)*Assumptions!$B$21*(1-Assumptions!$B$23) | M16: =D16*(1-Assumptions!$B$28) | N16: =M16-H16+L16-J16-K16-I16 | O16: =N16/I16 | P16: =O16*12/E16 | Q16: =D16/Assumptions!$B$7
... A22: B | B22: 1950000 | C22: Bull | D22: 2350000 | E22: 10 | F22: 1 | G22: 50000 | H22: =B22*Assumptions!$B$9 | I22: =B22+B22*Assumptions!$B$13+H22*Assumptions!$B$11+G22+Assumptions!$B$15-H22 | J22: =H22*Assumptions!$B$10*E22/12 | K22: =(Assumptions!$B$17+Assumptions!$B$18)*E22/12+Assumptions!$B$19*E22 | L22: =F22*MAX(0,E22-Assumptions!$B$22)*Assumptions!$B$21*(1-Assumptions!$B$23) | M22: =D22*(1-Assumptions!$B$28) | N22: =M22-H22+L22-J22-K22-I22 | O22: =N22/I22 | P22: =O22*12/E22 | Q22: =D22/Assumptions!$B$7

Sheet LP Waterfall
A1: Equity Waterfall — LP Syndication vs. Single-Partner JV
A2: Left: LP syndication (90/10 co-invest, pref, promote; GP co-invest is FIRST-LOSS). Right: JV (partner funds 100%, pref, split, no fees). Pulls base case from Deal Model.
A4: LP SYNDICATION | D4: JV ALTERNATIVE
A5: Total equity (from Deal Model) | B5: ='Deal Model'!B11 | D5: Capital partner funds (100% of equity) | E5: ='Deal Model'!B11
A6: Deal profit (from Deal Model) | B6: ='Deal Model'!B24 | D6: Deal profit | E6: ='Deal Model'!B24
A7: LP capital | B7: =B5*Assumptions!$B$30 | D7: Capital partner preferred | E7: =E5*Assumptions!$B$34*Assumptions!$B$27/12
A8: GP co-invest capital | B8: =B5-B7 | D8: Residual after pref | E8: =MAX(0,E6-E7)
A9: LP preferred (pro-rated for hold) | B9: =B7*Assumptions!$B$31*Assumptions!$B$27/12 | D9: Capital partner total profit | E9: =MIN(E6,E7)+E8*Assumptions!$B$35
A10: GP pref on co-invest | B10: =B8*Assumptions!$B$31*Assumptions!$B$27/12 | D10: Operator profit (sweat equity) | E10: =E6-E9
A11: Residual after prefs | B11: =MAX(0,B6-B9-B10) | D11: Capital partner annualized | E11: =E9/E5*12/Assumptions!$B$27
A12: LP total profit | B12: =IF(B6<B9, B6-MAX(MIN(0,B6),-B8), B9+B11*Assumptions!$B$32) | D12: Capital partner equity multiple | E12: =1+E9/E5
A13: GP total profit (promote + co-invest) | B13: =B6-B12
A14: LP return on capital (hold) | B14: =B12/B7
A15: LP annualized | B15: =B14*12/Assumptions!$B$27
A16: LP equity multiple | B16: =1+B14
A17: GP annualized on co-invest | B17: =IF(B8=0,0,B13/B8*12/Assumptions!$B$27)
A21: Dimension | B21: LP Syndication | C21: Single-Partner JV
A22: Sourcing, negotiation, MAO discipline | B22: GP (sponsor) | C22: Operator
A23: Capital | B23: LPs 90% / GP 10% first-loss | C23: Capital partner 100%
A24: Debt guarantee / carve-outs | B24: GP | C24: Negotiated (usually operator)
A25: Asset & lease management | B25: GP | C25: Operator
A26: Disposition decision | B26: GP (LP consent on major) | C26: Joint / dual-approval
A27: Reporting | B27: Monthly to LPs | C27: Direct, shared dashboard
A28: Fees | B28: None (promote only) | C28: None (split only)
A29: Decision speed | B29: Fast (GP controls) | C29: Slower (two signatures)
A30: Best when | B30: Multiple passive checks $50-250k | C30: One relationship writes the whole check

Sheet Rental-Refi Test
A1: Why Buy-and-Hold Rental is REJECTED (shown for discipline)
A2: The asset cannot carry itself as a rental at any financeable leverage — the thesis must be the sale, not the yield.
A4: Gross unfurnished rent / yr | B4: =Assumptions!$B$24*12
A5: Taxes (fully reassessed, non-homestead) | B5: =27000
A6: Insurance | B6: =Assumptions!$B$18
A7: Management | B7: =B4*Assumptions!$B$23
A8: Maintenance / reserves | B8: =6000
A9: NOI | B9: =B4-B5-B6-B7-B8
A10: Cap rate at ask price | B10: =B9/Assumptions!$B$5
A12: LTV | B12: Loan | C12: Debt service (IO) | D12: DSCR | E12: Lender floor
A13: 0.6 | B13: =Assumptions!$B$5*A13 | C13: =B13*Assumptions!$B$37 | D13: =$B$9/C13 | E13: 1.00–1.25
A14: 0.7 | B14: =Assumptions!$B$5*A14 | C14: =B14*Assumptions!$B$37 | D14: =$B$9/C14 | E14: 1.00–1.25
A15: 0.75 | B15: =Assumptions!$B$5*A15 | C15: =B15*Assumptions!$B$37 | D15: =$B$9/C15 | E15: 1.00–1.25
A17: Refi contingency: 75% cash-out at 7.75% needs ~$119k/yr debt service vs ~$41k furnished NOI → DSCR 0.34. Plan B is a price cut to the $2.0–2.05M comp floor (bear case), not a hold.

Sheet Comps & Market
A1: Comparable Sales & Market Data (researched July 2026)
A2: Full sourcing in MARKET_DATA.md. Subject: 5,120 sqft new 2025 build; ask $2.15M = $420/sqft after -20% cut from $2.695M.
A4: Address | B4: Sold price | C4: Date | D4: SqFt | E4: $/SqFt | F4: Bd/Ba | G4: Built | H4: Notes
A5: 477 Michael Dr, 30009 (same pocket) | B5: 2025000 | C5: Aug 2025 | D5: 4804 | E5: =B5/D5 | F5: 5/4.5 | G5: 2024 | H5: New construction; 92% of list, ~55 DOM — best comp
A6: 2444 Tenor Ln, 30009 (Avalon-adj.) | B6: 2224500 | C6: May 2025 | D6: 3506 | E6: =B6/D6 | F6: 3/3.5 | G6: 2024 | H6: Walkability premium, small format
A7: 135 Von Lake Dr, 30004 | B7: 2292500 | C7: Oct 2025 | D7: 7300 | E7: =B7/D7 | F7: 5/5.5 | G7: 2023 | H7: 1-acre; 95.6% of list, ~2.5 mo
A8: 2863 Stirling Ridge Ct, 30004 | B8: 2032500 | C8: Jun 2025 | D8: 5510 | E8: =B8/D8 | F8: 6/8 | G8: 2006 | H8: Resale estate — absorption datum
A9: 1070 Mid Broadwell Rd, 30004 | B9: 2630444 | C9: Jun 2023 | D9: 4822 | E9: =B9/D9 | F9: 5/5.5 | G9: 2023 | H9: High-water $/sqft precedent (2023)
A10: 289 Milton Ave, 30009 (downtown) | B10: 1844000 | C10: Jun 2023 | D10: 4617 | E10: =B10/D10 | F10: 5/4 | G10: 2017 | H10: Near-new resale, walkable
A13: SUBJECT TIMELINE
A14: Oct 2024 — lot/teardown acquired by builder | B14: $570,000
A15: Aug 2025 — listed (Ansley / Christie's, FMLS 7622905) | B15: $2,695,000 ($526/sqft)
A16: Feb 2026 — relisted, builder self-listing (FMLS 7719521) | B16: $2,150,000 ($420/sqft) — a 20.2% cut
A17: Jul 2026 — still ACTIVE; ~11 months cumulative market time | B17: possible further cut to ~$2.0M (unconfirmed)
A18: MARKET SNAPSHOT
A19: Comp support band (closed new construction) | B19: $420–470/sqft → $2.15M–$2.41M
A20: Alpharetta median sale price (2026) | B20: $724k–740k; 2.3 months supply; ~97% list-to-sale
A21: Alpharetta avg DOM 2025 / early 2026 | B21: ~34 days / ~21 days — subject is 10x+ over
A22: 30009 median $/sqft (all housing) | B22: $303, down ~4.6% YoY
A23: Median household income (Alpharetta) | B23: ~$147,000; ~900 tech firms; Milton HS 10/10
A24: Financing (mid-2026) | B24: Jumbo 6.6% | DSCR 7.0–7.5% | Bridge/HM ~9.5–10.2% + 2–3 pts | Cash-out 7.75%
A25: Rents: unfurnished / furnished exec | B25: $5.5–7.5k/mo / ~$8–11k/mo; thin depth above $7k
A26: Taxes non-homestead (31.7 mills x 40% AV) | B26: ~$27k/yr at $2.15M FMV; insurance ~$12k/yr
